mindflow_synth/__init__.py
mindflow_synth/main.py
mindflow_synth/prompts.py
mindflow_synth-2025.12.21184613.dist-info/METADATA
mindflow_synth-2025.12.21184613.dist-info/WHEEL
mindflow_synth-2025.12.21184613.dist-info/top_level.txt
mindflow_synth-2025.12.21184613.dist-info/RECORD
