Metadata-Version: 2.4
Name: mindflow-synth
Version: 2025.12.21184613
Summary: mindflow-synth extracts and structures insights on deep focus and flow from text, providing consistent, actionable summaries.
Author-email: mindflow-synth <hi@eugene.plus>
License: MIT
Project-URL: Homepage, https://github.com/chigwell/mindflow-synth
Requires-Python: >=3.9
Requires-Dist: langchain-llm7>=0.0.0
Requires-Dist: llmatch-messages>=0.0.0
Requires-Dist: langchain-core>=0.3.0
